scAAnet/__init__.py
scAAnet/api.py
scAAnet/loss.py
scAAnet/network.py
scAAnet/tools.py
scAAnet/train.py
scAAnet-1.0.0.dist-info/LICENSE
scAAnet-1.0.0.dist-info/METADATA
scAAnet-1.0.0.dist-info/WHEEL
scAAnet-1.0.0.dist-info/top_level.txt
scAAnet-1.0.0.dist-info/RECORD
