Metadata-Version: 2.1
Name: scAAnet
Version: 1.0.0
Summary: An implementation of nonlinear archetypal analysis on single-cell RNA-seq data through autoencoder
Home-page: https://github.com/AprilYuge/scAAnet_latest
Author: Yuge Wang
Author-email: wangyuge22@qq.com
License: UNKNOWN
Platform: UNKNOWN
Classifier: Programming Language :: Python :: 3
Classifier: License :: OSI Approved :: MIT License
Classifier: Operating System :: OS Independent
License-File: LICENSE
Requires-Dist: numpy
Requires-Dist: pandas
Requires-Dist: scipy
Requires-Dist: tensorflow
Requires-Dist: sklearn
Requires-Dist: fastcluster
Requires-Dist: statsmodels
Requires-Dist: seaborn
Requires-Dist: matplotlib
Requires-Dist: anndata
